ccbuilder/__init__.py
ccbuilder/__main__.py
ccbuilder/bisector.py
ccbuilder/cli.py
ccbuilder/compilerstore.py
ccbuilder/defaults.py
ccbuilder/py.typed
ccbuilder/builder/__init__.py
ccbuilder/builder/builder.py
ccbuilder/data/patches/gcc/0001-c-Implement-P1467R9-Extended-floating-point-types-an-alternative.patch
ccbuilder/data/patches/gcc/0001-c-Implement-P1467R9-Extended-floating-point-types-an-alternative2.patch
ccbuilder/data/patches/gcc/0001-c-Implement-P1467R9-Extended-floating-point-types-an.patch
ccbuilder/data/patches/gcc/0001-check_size_and_offset.patch
ccbuilder/data/patches/gcc/0001-fixinc-don-t-fix-machine-names-in-__has_include-.-PR.patch
ccbuilder/data/patches/gcc/0001-linux-fs.patch
ccbuilder/data/patches/gcc/0001-malloc-attribute.patch
ccbuilder/data/patches/gcc/0001-malloc-attributes-patch.patch
ccbuilder/data/patches/gcc/gcc-fix-simple-object-decl-and-use-in-gcc-lto.patch
ccbuilder/data/patches/gcc/gcc-libsanitizer.sh
ccbuilder/data/patches/gcc/gcc-simple-object-declaration.patch
ccbuilder/data/patches/gcc/gcc-ustat.patch
ccbuilder/data/patches/llvm/0001-uintptr_t-patch.patch
ccbuilder/data/patches/llvm/llvm-GCOpenMPRuntime.cpp-lambda-issues.patch
ccbuilder/data/patches/llvm/llvm-MicrosoftDemangleNodes-missing-includes.patch
ccbuilder/data/patches/llvm/llvm-MicrosoftDemangleNodes.h-fix-includes.patch
ccbuilder/utils/__init__.py
ccbuilder/utils/utils.py
ccbuilder-0.1.2.dist-info/LICENSE
ccbuilder-0.1.2.dist-info/METADATA
ccbuilder-0.1.2.dist-info/WHEEL
ccbuilder-0.1.2.dist-info/entry_points.txt
ccbuilder-0.1.2.dist-info/top_level.txt
ccbuilder-0.1.2.dist-info/RECORD
