Metadata-Version: 2.1
Name: ccbuilder
Version: 0.1.2
Summary: A clang/gcc compiler builder
Home-page: https://github.com/DeadCodeProductions/ccbuilder
Author: Theodoros Theodoridis, Yann Girsberger
Author-email: theodort@inf.ethz.ch
License: Apache License 2.0
Classifier: Programming Language :: Python :: 3
Requires-Python: >=3.10
License-File: LICENSE
Requires-Dist: diopter >=0.0.24
